clarus/__init__.py
clarus/api.py
clarus/api_config.py
clarus/models.py
clarus/multipart.py
clarus/output_types.py
clarus/resource_util.py
clarus/services/__init__.py
clarus/services/apps.py
clarus/services/ccp.py
clarus/services/ccpqd.py
clarus/services/compliance.py
clarus/services/credit.py
clarus/services/dates.py
clarus/services/etd.py
clarus/services/frtb.py
clarus/services/hedge.py
clarus/services/load.py
clarus/services/margin.py
clarus/services/market.py
clarus/services/mifid.py
clarus/services/portfolio.py
clarus/services/profitloss.py
clarus/services/risk.py
clarus/services/sbsdr.py
clarus/services/sdr.py
clarus/services/sef.py
clarus/services/simm.py
clarus/services/trade.py
clarus/services/util.py
clarus/services/xva.py
clarusx/__init__.py
clarus-0.1.105.dist-info/METADATA
clarus-0.1.105.dist-info/WHEEL
clarus-0.1.105.dist-info/top_level.txt
clarus-0.1.105.dist-info/RECORD
