Metadata-Version: 2.4
Name: clarus
Version: 0.1.105
Summary: Clarus Microservices
Home-page: http://www.clarusft.com
Author: Clarus Financial Technology
Author-email: support@clarusft.com
Requires-Dist: requests
Requires-Dist: six
Requires-Dist: requests-toolbelt
Requires-Dist: websocket-client
Dynamic: author
Dynamic: author-email
Dynamic: home-page
Dynamic: requires-dist
Dynamic: summary
